src/container_mngr/__init__.py
src/container_mngr/__main__.py
src/container_mngr/__version__.py
src/container_mngr/app.py
src/container_mngr/components/__init__.py
src/container_mngr/components/containers.py
src/container_mngr/components/images.py
src/container_mngr/components/runtime.py
src/container_mngr/components/screens.py
src/container_mngr/components/table_wrapper.py
src/container_mngr/container_mngr_app.css
src/container_mngr/data/__init__.py
src/container_mngr/data/docker.py
src/container_mngr/data/errors.py
src/container_mngr/data/models.py
container_mngr-0.3.0.dist-info/METADATA
container_mngr-0.3.0.dist-info/WHEEL
container_mngr-0.3.0.dist-info/RECORD
