Metadata-Version: 2.1
Name: container-mngr
Version: 0.3.0
Summary: Simple console application for managing Docker containers
Author: Stefan Szarek
Author-email: stefan.szarek@gmail.com
Requires-Python: >=3.10,<4.0
Classifier: Programming Language :: Python :: 3
Classifier: Programming Language :: Python :: 3.10
Classifier: Programming Language :: Python :: 3.11
Requires-Dist: docker (>=6.0.1,<7.0.0)
Requires-Dist: pypiwin32 (>=223,<224) ; sys_platform == "win32"
Requires-Dist: python-dateutil (>=2.8.2,<3.0.0)
Requires-Dist: textual (>=0.5.0,<0.6.0)
